librix/__init__.py
librix/api.py
librix/scraper.py
librix-0.1.0.dist-info/METADATA
librix-0.1.0.dist-info/WHEEL
librix-0.1.0.dist-info/entry_points.txt
librix-0.1.0.dist-info/licenses/LICENSE
librix-0.1.0.dist-info/RECORD
