Metadata-Version: 2.4
Name: librix
Version: 0.1.0
Summary: A professional API and scraper for Anna's Archive
Author-email: Kosma Gąsiorowski <kosma@example.com>
License: MIT
License-File: LICENSE
Requires-Python: >=3.10
Requires-Dist: beautifulsoup4>=4.12.0
Requires-Dist: fastapi>=0.109.0
Requires-Dist: requests>=2.31.0
Requires-Dist: uvicorn>=0.27.0
